[
    {
        "transactionName": "WebTours",
        "rawStartTime": 1607121898695,
        "rawEndTime": 1607121898917
    },
    {
        "transactionName": "LoginUser",
        "rawStartTime": 1607121898949,
        "rawEndTime": 1607121899154
    },
    {
        "transactionName": "SearchReis",
        "rawStartTime": 1607121899170,
        "rawEndTime": 1607121899409
    },
    {
        "transactionName": "ChousReis",
        "rawStartTime": 1607121899426,
        "rawEndTime": 1607121899504
    },
    {
        "transactionName": "InputPassData",
        "rawStartTime": 1607121899537,
        "rawEndTime": 1607121899631
    },
    {
        "transactionName": "Logout",
        "rawStartTime": 1607121899646,
        "rawEndTime": 1607121899756
    },
    {
        "transactionName": "02_FlightsReservation",
        "rawStartTime": 1607121898681,
        "rawEndTime": 1607121899772
    }
]