<?xml version="1.0" encoding="windows-1251"?><Metadata><Ms><It Ln="31" O="0" M="Utt.Debugger.Error" T="undeclared identifier `Users'&#xD;&#xA;"><P F="C:\Users\user\Documents\GitHub\KursLoadRunner\Скрипты\01_UserRegistration\Action.c" N="21" C="0" /></It><It Ln="30" O="0" M="Utt.Debugger.Error" T="type error: pointer expected&#xD;&#xA;"><P F="C:\Users\user\Documents\GitHub\KursLoadRunner\Скрипты\01_UserRegistration\Action.c" N="21" C="0" /></It><It Ln="30" O="0" M="Utt.Debugger.Error" T="type error: pointer expected&#xD;&#xA;"><P F="C:\Users\user\Documents\GitHub\KursLoadRunner\Скрипты\01_UserRegistration\Action.c" N="21" C="0" /></It><It Ln="43" O="0" M="Utt.Debugger.Warning" T="warning: expression with no effect elided&#xD;&#xA;"><P F="C:\Users\user\Documents\GitHub\KursLoadRunner\Скрипты\01_UserRegistration\Action.c" N="21" C="0" /></It><It Ln="41" O="0" M="Utt.Debugger.Error" T="syntax error; found `int' expecting `;'&#xD;&#xA;"><P F="C:\Users\user\Documents\GitHub\KursLoadRunner\Скрипты\01_UserRegistration\Action.c" N="23" C="0" /></It><It Ln="41" O="0" M="Utt.Debugger.Error" T="syntax error; found `int' expecting `;'&#xD;&#xA;"><P F="C:\Users\user\Documents\GitHub\KursLoadRunner\Скрипты\01_UserRegistration\Action.c" N="23" C="0" /></It><It Ln="41" O="0" M="Utt.Debugger.Error" T="syntax error; found `int' expecting `)'&#xD;&#xA;"><P F="C:\Users\user\Documents\GitHub\KursLoadRunner\Скрипты\01_UserRegistration\Action.c" N="23" C="0" /></It><It Ln="16" O="0" M="Utt.Debugger.Error" T="skipping `int'&#xD;&#xA;"><P F="C:\Users\user\Documents\GitHub\KursLoadRunner\Скрипты\01_UserRegistration\Action.c" N="23" C="0" /></It><It Ln="27" O="0" M="Utt.Debugger.Error" T="undeclared identifier `i'&#xD;&#xA;"><P F="C:\Users\user\Documents\GitHub\KursLoadRunner\Скрипты\01_UserRegistration\Action.c" N="23" C="0" /></It><It Ln="43" O="0" M="Utt.Debugger.Warning" T="warning: expression with no effect elided&#xD;&#xA;"><P F="C:\Users\user\Documents\GitHub\KursLoadRunner\Скрипты\01_UserRegistration\Action.c" N="23" C="0" /></It><It Ln="27" O="0" M="Utt.Debugger.Warning" T="warning: unreachable code&#xD;&#xA;"><P F="C:\Users\user\Documents\GitHub\KursLoadRunner\Скрипты\01_UserRegistration\Action.c" N="23" C="0" /></It><It Ln="39" O="0" M="Utt.Debugger.Error" T="syntax error; found `)' expecting `;'&#xD;&#xA;"><P F="C:\Users\user\Documents\GitHub\KursLoadRunner\Скрипты\01_UserRegistration\Action.c" N="23" C="0" /></It><It Ln="31" O="0" M="Utt.Debugger.Error" T="illegal statement termination&#xD;&#xA;"><P F="C:\Users\user\Documents\GitHub\KursLoadRunner\Скрипты\01_UserRegistration\Action.c" N="23" C="0" /></It><It Ln="14" O="0" M="Utt.Debugger.Error" T="skipping `)'&#xD;&#xA;"><P F="C:\Users\user\Documents\GitHub\KursLoadRunner\Скрипты\01_UserRegistration\Action.c" N="23" C="0" /></It><It Ln="41" O="0" M="Utt.Debugger.Error" T="syntax error; found `int' expecting `;'&#xD;&#xA;"><P F="C:\Users\user\Documents\GitHub\KursLoadRunner\Скрипты\01_UserRegistration\Action.c" N="24" C="0" /></It><It Ln="41" O="0" M="Utt.Debugger.Error" T="syntax error; found `int' expecting `;'&#xD;&#xA;"><P F="C:\Users\user\Documents\GitHub\KursLoadRunner\Скрипты\01_UserRegistration\Action.c" N="24" C="0" /></It><It Ln="41" O="0" M="Utt.Debugger.Error" T="syntax error; found `int' expecting `)'&#xD;&#xA;"><P F="C:\Users\user\Documents\GitHub\KursLoadRunner\Скрипты\01_UserRegistration\Action.c" N="24" C="0" /></It><It Ln="16" O="0" M="Utt.Debugger.Error" T="skipping `int'&#xD;&#xA;"><P F="C:\Users\user\Documents\GitHub\KursLoadRunner\Скрипты\01_UserRegistration\Action.c" N="24" C="0" /></It><It Ln="27" O="0" M="Utt.Debugger.Error" T="undeclared identifier `j'&#xD;&#xA;"><P F="C:\Users\user\Documents\GitHub\KursLoadRunner\Скрипты\01_UserRegistration\Action.c" N="24" C="0" /></It><It Ln="43" O="0" M="Utt.Debugger.Warning" T="warning: expression with no effect elided&#xD;&#xA;"><P F="C:\Users\user\Documents\GitHub\KursLoadRunner\Скрипты\01_UserRegistration\Action.c" N="24" C="0" /></It><It Ln="27" O="0" M="Utt.Debugger.Warning" T="warning: unreachable code&#xD;&#xA;"><P F="C:\Users\user\Documents\GitHub\KursLoadRunner\Скрипты\01_UserRegistration\Action.c" N="24" C="0" /></It><It Ln="39" O="0" M="Utt.Debugger.Error" T="syntax error; found `)' expecting `;'&#xD;&#xA;"><P F="C:\Users\user\Documents\GitHub\KursLoadRunner\Скрипты\01_UserRegistration\Action.c" N="24" C="0" /></It><It Ln="31" O="0" M="Utt.Debugger.Error" T="illegal statement termination&#xD;&#xA;"><P F="C:\Users\user\Documents\GitHub\KursLoadRunner\Скрипты\01_UserRegistration\Action.c" N="24" C="0" /></It><It Ln="14" O="0" M="Utt.Debugger.Error" T="skipping `)'&#xD;&#xA;"><P F="C:\Users\user\Documents\GitHub\KursLoadRunner\Скрипты\01_UserRegistration\Action.c" N="24" C="0" /></It><It Ln="30" O="0" M="Utt.Debugger.Error" T="type error: pointer expected&#xD;&#xA;"><P F="C:\Users\user\Documents\GitHub\KursLoadRunner\Скрипты\01_UserRegistration\Action.c" N="25" C="0" /></It><It Ln="17" O="0" M="Utt.Debugger.Error" T="too many errors&#xD;&#xA;"><P F="C:\Users\user\Documents\GitHub\KursLoadRunner\Скрипты\01_UserRegistration\Action.c" N="25" C="0" /></It></Ms></Metadata>