[
    {
        "stepId": "STEP1",
        "stepName": "Url: WebTours",
        "infFile": "t1.inf",
        "time": 1594159369462
    },
    {
        "stepId": "STEP2",
        "stepName": "Submit Form: login.pl",
        "infFile": "t2.inf",
        "time": 1594159369672
    },
    {
        "stepId": "STEP3",
        "stepName": "Image: Search Flights Button",
        "infFile": "t3.inf",
        "time": 1594159369896
    },
    {
        "stepId": "STEP4",
        "stepName": "Submit Form: reservations.pl",
        "infFile": "t4.inf",
        "time": 1594159369962
    },
    {
        "stepId": "STEP5",
        "stepName": "Submit Form: reservations.pl_2",
        "infFile": "t5.inf",
        "time": 1594159370046
    },
    {
        "stepId": "STEP6",
        "stepName": "Image: SignOff Button",
        "infFile": "t6.inf",
        "time": 1594159370255
    }
]